{
  "as_of_utc": "2026-06-29T00:00:00Z",
  "canary_members": [
    "OLLI",
    "MAS",
    "BLDR",
    "BLD",
    "OC",
    "FIVE",
    "KBH",
    "URBN",
    "TGT",
    "BBY",
    "DDS",
    "LEN",
    "WSM",
    "MTH",
    "FND",
    "ANF",
    "EBAY",
    "LOW",
    "DHI",
    "BBW",
    "AEO",
    "PHM",
    "DKS",
    "M",
    "BBWI"
  ],
  "CanaryEW": {
    "1D": -0.01640443643324474,
    "3M": 0.14947202427038198,
    "YTD": 0.018605601347229994,
    "12M": 0.17729091760894689
  },
  "CanaryMC": {
    "1D": -0.013468889765900105,
    "3M": 0.14354903970959165,
    "YTD": 0.10033101821448898,
    "12M": 0.21747744182548534
  },
  "leaders_laggards": {
    "1D": {
      "best": {
        "ticker": "OC",
        "return": 0.15259623129660027
      },
      "worst": {
        "ticker": "BLD",
        "return": -0.15454028235071704
      },
      "top_contributor_mc": {
        "ticker": "OC",
        "contribution": 0.003792843889030855
      },
      "bottom_contributor_mc": {
        "ticker": "TGT",
        "contribution": -0.005544482300981655
      }
    },
    "3M": {
      "best": {
        "ticker": "OC",
        "return": 0.49587810111448993
      },
      "worst": {
        "ticker": "OLLI",
        "return": -0.19935792823673315
      },
      "top_contributor_mc": {
        "ticker": "EBAY",
        "contribution": 0.025536318434061817
      },
      "bottom_contributor_mc": {
        "ticker": "LOW",
        "contribution": -0.012438289909788009
      }
    },
    "YTD": {
      "best": {
        "ticker": "OC",
        "return": 0.3865685695633694
      },
      "worst": {
        "ticker": "BBW",
        "return": -0.49666155003281753
      },
      "top_contributor_mc": {
        "ticker": "TGT",
        "contribution": 0.043150994729573074
      },
      "bottom_contributor_mc": {
        "ticker": "LOW",
        "contribution": -0.024858643763142903
      }
    },
    "12M": {
      "best": {
        "ticker": "M",
        "return": 1.177281950223355
      },
      "worst": {
        "ticker": "OLLI",
        "return": -0.45113065335361047
      },
      "top_contributor_mc": {
        "ticker": "TGT",
        "contribution": 0.05016103708185512
      },
      "bottom_contributor_mc": {
        "ticker": "LEN",
        "contribution": -0.007233871637161375
      }
    }
  }
}