{
  "as_of_utc": "2026-03-25T00:00:00Z",
  "canary_members": [
    "OLLI",
    "MAS",
    "BLDR",
    "BLD",
    "OC",
    "FIVE",
    "KBH",
    "URBN",
    "TGT",
    "BBY",
    "DDS",
    "LEN",
    "WSM",
    "MTH",
    "FND",
    "ANF",
    "EBAY",
    "LOW",
    "DHI",
    "BBW",
    "AEO",
    "PHM",
    "DKS",
    "M",
    "BBWI"
  ],
  "CanaryEW": {
    "1D": 0.002697336410789286,
    "3M": -0.10204007764592338,
    "YTD": -0.10151362303722378,
    "12M": 0.08433517535120771
  },
  "CanaryMC": {
    "1D": 0.0041875611879487185,
    "3M": -0.018437910400637247,
    "YTD": -0.021990043256645886,
    "12M": 0.09936453820861546
  },
  "leaders_laggards": {
    "1D": {
      "best": {
        "ticker": "BLD",
        "return": 0.037440902712773116
      },
      "worst": {
        "ticker": "BBW",
        "return": -0.034583583442505006
      },
      "top_contributor_mc": {
        "ticker": "LOW",
        "contribution": 0.002130886575646614
      },
      "bottom_contributor_mc": {
        "ticker": "BBY",
        "contribution": -0.0006061784550071096
      }
    },
    "3M": {
      "best": {
        "ticker": "FIVE",
        "return": 0.23044917924846464
      },
      "worst": {
        "ticker": "AEO",
        "return": -0.3704570998400274
      },
      "top_contributor_mc": {
        "ticker": "TGT",
        "contribution": 0.020658787277215557
      },
      "bottom_contributor_mc": {
        "ticker": "LOW",
        "contribution": -0.008463933120733739
      }
    },
    "YTD": {
      "best": {
        "ticker": "FIVE",
        "return": 0.20780562203367592
      },
      "worst": {
        "ticker": "AEO",
        "return": -0.3704570998400274
      },
      "top_contributor_mc": {
        "ticker": "TGT",
        "contribution": 0.019370407358702785
      },
      "bottom_contributor_mc": {
        "ticker": "LOW",
        "contribution": -0.011156509149722951
      }
    },
    "12M": {
      "best": {
        "ticker": "FIVE",
        "return": 2.034021392223288
      },
      "worst": {
        "ticker": "BBWI",
        "return": -0.41472932179525335
      },
      "top_contributor_mc": {
        "ticker": "FIVE",
        "contribution": 0.054936847777212534
      },
      "bottom_contributor_mc": {
        "ticker": "LEN",
        "contribution": -0.00987532482204595
      }
    }
  }
}