{
  "as_of_utc": "2026-02-06T00:00:00Z",
  "canary_members": [
    "OLLI",
    "MAS",
    "BLDR",
    "BLD",
    "OC",
    "FIVE",
    "KBH",
    "URBN",
    "TGT",
    "BBY",
    "DDS",
    "LEN",
    "WSM",
    "MTH",
    "FND",
    "ANF",
    "EBAY",
    "LOW",
    "DHI",
    "BBW",
    "AEO",
    "PHM",
    "DKS",
    "M",
    "BBWI"
  ],
  "CanaryEW": {
    "1D": 0.028582122512206265,
    "3M": 0.1715750459236185,
    "YTD": 0.07800177142036469,
    "12M": 0.15184100424254887
  },
  "CanaryMC": {
    "1D": 0.021000062716337586,
    "3M": 0.1679997248954661,
    "YTD": 0.11445292695562648,
    "12M": 0.12340886083516822
  },
  "leaders_laggards": {
    "1D": {
      "best": {
        "ticker": "M",
        "return": 0.05483272676930073
      },
      "worst": {
        "ticker": "ANF",
        "return": -0.014530724865629119
      },
      "top_contributor_mc": {
        "ticker": "TGT",
        "contribution": 0.00419543851552638
      },
      "bottom_contributor_mc": {
        "ticker": "DHI",
        "contribution": -0.000990760749048661
      }
    },
    "3M": {
      "best": {
        "ticker": "AEO",
        "return": 0.4378017811217896
      },
      "worst": {
        "ticker": "BBY",
        "return": -0.09317658313682897
      },
      "top_contributor_mc": {
        "ticker": "LOW",
        "contribution": 0.06110155230111057
      },
      "bottom_contributor_mc": {
        "ticker": "LEN",
        "contribution": -0.002560597219547359
      }
    },
    "YTD": {
      "best": {
        "ticker": "BLD",
        "return": 0.19944370230236008
      },
      "worst": {
        "ticker": "ANF",
        "return": -0.21076446300227591
      },
      "top_contributor_mc": {
        "ticker": "LOW",
        "contribution": 0.03882672759057974
      },
      "bottom_contributor_mc": {
        "ticker": "ANF",
        "contribution": -0.001735246543797299
      }
    },
    "12M": {
      "best": {
        "ticker": "FIVE",
        "return": 1.1568021646233904
      },
      "worst": {
        "ticker": "BBWI",
        "return": -0.3649663335686081
      },
      "top_contributor_mc": {
        "ticker": "LOW",
        "contribution": 0.0308117395831467
      },
      "bottom_contributor_mc": {
        "ticker": "TGT",
        "contribution": -0.010309534695199005
      }
    }
  }
}