{
  "as_of_utc": "2026-02-20T00:00:00Z",
  "canary_members": [
    "OLLI",
    "MAS",
    "BLDR",
    "BLD",
    "OC",
    "FIVE",
    "KBH",
    "URBN",
    "TGT",
    "BBY",
    "DDS",
    "LEN",
    "WSM",
    "MTH",
    "FND",
    "ANF",
    "EBAY",
    "LOW",
    "DHI",
    "BBW",
    "AEO",
    "PHM",
    "DKS",
    "M",
    "BBWI"
  ],
  "CanaryEW": {
    "1D": 0.008459882046695233,
    "3M": 0.2124293428112849,
    "YTD": 0.078221431452689,
    "12M": 0.17711250166809855
  },
  "CanaryMC": {
    "1D": 0.010066845434318683,
    "3M": 0.2045859158487633,
    "YTD": 0.1197014123869089,
    "12M": 0.16260182791870104
  },
  "leaders_laggards": {
    "1D": {
      "best": {
        "ticker": "FND",
        "return": 0.04340585296385013
      },
      "worst": {
        "ticker": "BBY",
        "return": -0.027450974525648486
      },
      "top_contributor_mc": {
        "ticker": "EBAY",
        "contribution": 0.0028664004345021546
      },
      "bottom_contributor_mc": {
        "ticker": "BBY",
        "contribution": -0.0006868572359095662
      }
    },
    "3M": {
      "best": {
        "ticker": "BBWI",
        "return": 0.5738588402590916
      },
      "worst": {
        "ticker": "BBY",
        "return": -0.11450944333845015
      },
      "top_contributor_mc": {
        "ticker": "LOW",
        "contribution": 0.06805480858147034
      },
      "bottom_contributor_mc": {
        "ticker": "BBY",
        "contribution": -0.002865167488443944
      }
    },
    "YTD": {
      "best": {
        "ticker": "BLD",
        "return": 0.20273488985591337
      },
      "worst": {
        "ticker": "ANF",
        "return": -0.22086628958688748
      },
      "top_contributor_mc": {
        "ticker": "LOW",
        "contribution": 0.041113008714502394
      },
      "bottom_contributor_mc": {
        "ticker": "ANF",
        "contribution": -0.0018284079376161965
      }
    },
    "12M": {
      "best": {
        "ticker": "FIVE",
        "return": 1.4684834824813158
      },
      "worst": {
        "ticker": "BBWI",
        "return": -0.3707311283204988
      },
      "top_contributor_mc": {
        "ticker": "LOW",
        "contribution": 0.046957148387287935
      },
      "bottom_contributor_mc": {
        "ticker": "BBY",
        "contribution": -0.006326376330311074
      }
    }
  }
}