{
  "as_of_utc": "2025-09-08T00:00:00Z",
  "canary_members": [
    "OLLI",
    "HBI",
    "MAS",
    "BLDR",
    "BLD",
    "OC",
    "FIVE",
    "KBH",
    "URBN",
    "TGT",
    "BBY",
    "DDS",
    "LEN",
    "WSM",
    "MTH",
    "FND",
    "ANF",
    "EBAY",
    "LOW",
    "DHI",
    "BBW",
    "AEO",
    "PHM",
    "DKS",
    "M",
    "BBWI"
  ],
  "CanaryEW": {
    "1D": 0.003996732166015704,
    "3M": 0.2622829216247313,
    "YTD": 0.13787374709275113,
    "12M": 0.19531796798017997
  },
  "CanaryMC": {
    "1D": 0.00493607537324392,
    "3M": 0.2356275791831648,
    "YTD": 0.14382868947758798,
    "12M": 0.12198289428849529
  },
  "leaders_laggards": {
    "1D": {
      "best": {
        "ticker": "BBW",
        "return": 0.11234902813772996
      },
      "worst": {
        "ticker": "BBWI",
        "return": -0.03162190785450192
      },
      "top_contributor_mc": {
        "ticker": "LOW",
        "contribution": 0.003171374319033809
      },
      "bottom_contributor_mc": {
        "ticker": "TGT",
        "contribution": -0.001377608383413051
      }
    },
    "3M": {
      "best": {
        "ticker": "AEO",
        "return": 0.7904550321104342
      },
      "worst": {
        "ticker": "TGT",
        "return": -0.04989936596517808
      },
      "top_contributor_mc": {
        "ticker": "LOW",
        "contribution": 0.06385095600105815
      },
      "bottom_contributor_mc": {
        "ticker": "TGT",
        "contribution": -0.0038351371220381467
      }
    },
    "YTD": {
      "best": {
        "ticker": "BBW",
        "return": 0.6469317391911231
      },
      "worst": {
        "ticker": "ANF",
        "return": -0.37751242514864225
      },
      "top_contributor_mc": {
        "ticker": "EBAY",
        "contribution": 0.0401953628839221
      },
      "bottom_contributor_mc": {
        "ticker": "TGT",
        "contribution": -0.024001508069310947
      }
    },
    "12M": {
      "best": {
        "ticker": "BBW",
        "return": 1.3543176972181548
      },
      "worst": {
        "ticker": "TGT",
        "return": -0.36895050920316286
      },
      "top_contributor_mc": {
        "ticker": "EBAY",
        "contribution": 0.04639763388821867
      },
      "bottom_contributor_mc": {
        "ticker": "TGT",
        "contribution": -0.02835658863936984
      }
    }
  }
}